{"rating": "5", "uuid": "448", "review_date": "2009-01-30", "helpful": "1", "reviewer_id": "A3JWXE8KE124BV", "not_helpful": "1", "review_text": "I bought this machine for my husband following the recommendations here. Consequently I also bought him the extra freezing container and two books of recipes,one being the Ben and Jerry's book. So far he has produced several excellent batches of ice cream. We are delighted and impressed! It's so easy and so much fun!", "summary": "Carefree ice cream!", "product_name": "Cuisinart ICE-20 Automatic 1-1/2-Quart Ice Cream Maker, White", "product_id": "B00000JGRT"}