{"rating": "1", "uuid": "318", "review_date": "2009-01-03", "helpful": "1", "reviewer_id": "A8K72KIDFS0N8", "not_helpful": "1", "review_text": "This blender sounds louder than a jet plane and when you're through holding it together, the food looks the same as when you put it in. IT DOES NOT BLEND! a terrible product. i've been disappointed in this brand name before, but this unblender surpasses even their worst.", "summary": "If i could only give a negative star", "product_name": "Cuisinart SPB-7 SmartPower 40-Ounce 7-Speed Electronic Bar Blender, White DISCONTINUED BY MANUFACTURER", "product_id": "B00000JGRQ"}