{"rating": "1", "uuid": "128", "review_date": "2013-07-11", "helpful": "7", "reviewer_id": "A134SOAMYBO1JZ", "not_helpful": "9", "review_text": "If you type the wrong word in, it &#34;might&#34; produce the correct word.  It doesn't give any explanation of the meaning or how it can be used. I should have sent it bk., but I factored in the cost of return shipping - wasn't worth the return.", "summary": "It doesn't do much.", "product_name": "Franklin SPELLING CORRECTOR", "product_id": "1567120709"}