{"rating": "5", "uuid": "786", "review_date": "2014-06-15", "helpful": "0", "reviewer_id": "A2RE9P12YH19TJ", "not_helpful": "0", "review_text": "i rate this product 5 stars for its quality to price ratio and simple yet practical designalthough i can tell this is not the &#34;best&#34; or most expensive pressure cooker in the market, it certainly is good enough for my family. so far i have made great indian food successfully with no problems and its fairly simple to clean", "summary": "nice economical cooker", "product_name": "Presto 01341 4-Quart Stainless Steel Pressure Cooker", "product_id": "B00002N602"}