{"rating": "5", "uuid": "702", "review_date": "2014-01-07", "helpful": "1", "reviewer_id": "A3BF2FURD4YD0Y", "not_helpful": "1", "review_text": "I have had a few pressure cookers in the past and have found that they are still so useful even with all of our other technologies on the market today.  This one is a 4 quart, very easy and fast to use.  I used it when I had a family of 5, and is still useful today with just my husband and I.  I recommend this product.", "summary": "love it!", "product_name": "Presto 01241 4-Quart Aluminum Pressure Cooker", "product_id": "B00002N601"}